academic_paper_assistant/__init__.py
academic_paper_assistant-0.0.1.dist-info/LICENSE
academic_paper_assistant-0.0.1.dist-info/METADATA
academic_paper_assistant-0.0.1.dist-info/WHEEL
academic_paper_assistant-0.0.1.dist-info/entry_points.txt
academic_paper_assistant-0.0.1.dist-info/top_level.txt
academic_paper_assistant-0.0.1.dist-info/RECORD
